imperfekt/__init__.py
imperfekt/analysis/README.md
imperfekt/analysis/__init__.py
imperfekt/analysis/imperfekt.png
imperfekt/analysis/imperfekt.py
imperfekt/analysis/intervariable/README.md
imperfekt/analysis/intervariable/__init__.py
imperfekt/analysis/intervariable/asymmetric_analysis.py
imperfekt/analysis/intervariable/html_report_generator.py
imperfekt/analysis/intervariable/intervariable.py
imperfekt/analysis/intervariable/marmnar.py
imperfekt/analysis/intervariable/mcar.py
imperfekt/analysis/intervariable/row_statistics.py
imperfekt/analysis/intervariable/symmetric_correlation.py
imperfekt/analysis/intravariable/README.md
imperfekt/analysis/intravariable/__init__.py
imperfekt/analysis/intravariable/autocorrelation.py
imperfekt/analysis/intravariable/column_statistics.py
imperfekt/analysis/intravariable/date_time_statistics.py
imperfekt/analysis/intravariable/gap_statistics.py
imperfekt/analysis/intravariable/html_report_generator.py
imperfekt/analysis/intravariable/intravariable.py
imperfekt/analysis/intravariable/markov_chain_summary.py
imperfekt/analysis/intravariable/windowed_significance.py
imperfekt/analysis/preliminary/README.md
imperfekt/analysis/preliminary/html_report_generator.py
imperfekt/analysis/preliminary/preliminary.py
imperfekt/analysis/utils/events.py
imperfekt/analysis/utils/html_reporting_helpers.py
imperfekt/analysis/utils/kruskal_wallis.py
imperfekt/analysis/utils/masking.py
imperfekt/analysis/utils/pretty_printing.py
imperfekt/analysis/utils/statistics_utils.py
imperfekt/analysis/utils/visualization_utils.py
imperfekt/config/global_settings.py
imperfekt/features/README.md
imperfekt/features/__init__.py
imperfekt/features/core.py
imperfekt/features/interaction.py
imperfekt/features/temporal.py
imperfekt/features/window.py
imperfekt-0.2.5.dist-info/METADATA
imperfekt-0.2.5.dist-info/WHEEL
imperfekt-0.2.5.dist-info/licenses/LICENSE
imperfekt-0.2.5.dist-info/RECORD
