Metadata-Version: 2.4
Name: imperfekt
Version: 0.2.5
Summary: A framework to analyze imperfections (missingness, noise) in time-series datasets.
Project-URL: Homepage, https://github.com/krafftta/imperfekt
Project-URL: Repository, https://github.com/krafftta/imperfekt
Project-URL: Issues, https://github.com/krafftta/imperfekt/issues
Author: Tamara Krafft
License-Expression: MIT
License-File: LICENSE
Keywords: data-quality,healthcare,missing-data,missingness-analysis,polars,time-series
Classifier: Development Status :: 4 - Beta
Classifier: Intended Audience :: Healthcare Industry
Classifier: Intended Audience :: Science/Research
Classifier: License :: OSI Approved :: MIT License
Classifier: Operating System :: OS Independent
Classifier: Programming Language :: Python :: 3
Classifier: Programming Language :: Python :: 3.10
Classifier: Programming Language :: Python :: 3.11
Classifier: Programming Language :: Python :: 3.12
Classifier: Topic :: Scientific/Engineering :: Information Analysis
Classifier: Typing :: Typed
Requires-Python: >=3.10
Requires-Dist: kaleido>=0.2.1
Requires-Dist: matplotlib>=3.8.0
Requires-Dist: missingno>=0.5.2
Requires-Dist: numpy>=1.24.0
Requires-Dist: pandas>=2.0.0
Requires-Dist: pingouin>=0.5.0
Requires-Dist: plotly>=5.18.0
Requires-Dist: polars>=0.20.0
Requires-Dist: rich>=13.0.0
Requires-Dist: scikit-learn>=1.3.0
Requires-Dist: scikit-posthocs>=0.9.0
Requires-Dist: scipy>=1.13.0
Requires-Dist: statsmodels>=0.14.0
Requires-Dist: upsetty>=0.1.0
Provides-Extra: dev
Requires-Dist: mypy>=1.7.0; extra == 'dev'
Requires-Dist: pre-commit>=3.5.0; extra == 'dev'
Requires-Dist: pytest-cov>=4.1.0; extra == 'dev'
Requires-Dist: pytest>=7.4.0; extra == 'dev'
Requires-Dist: ruff>=0.1.0; extra == 'dev'
Provides-Extra: docs
Requires-Dist: mkdocs-material>=9.5.0; extra == 'docs'
Requires-Dist: mkdocs>=1.5.0; extra == 'docs'
Requires-Dist: mkdocstrings[python]>=0.24.0; extra == 'docs'
